MANIFEST.in
README.txt
setup.cfg
setup.py
docs/HISTORY.txt
docs/INSTALL.txt
docs/LICENSE.GPL
docs/LICENSE.txt
jalonedit/__init__.py
jalonedit.theme.egg-info/PKG-INFO
jalonedit.theme.egg-info/SOURCES.txt
jalonedit.theme.egg-info/dependency_links.txt
jalonedit.theme.egg-info/entry_points.txt
jalonedit.theme.egg-info/namespace_packages.txt
jalonedit.theme.egg-info/not-zip-safe
jalonedit.theme.egg-info/paster_plugins.txt
jalonedit.theme.egg-info/requires.txt
jalonedit.theme.egg-info/top_level.txt
jalonedit/theme/__init__.py
jalonedit/theme/configure.zcml
jalonedit/theme/profiles.zcml
jalonedit/theme/skins.zcml
jalonedit/theme/tests.py
jalonedit/theme/version.txt
jalonedit/theme/browser/__init__.py
jalonedit/theme/browser/configure.zcml
jalonedit/theme/browser/interfaces.py
jalonedit/theme/browser/images/16px-Open_book.png
jalonedit/theme/browser/images/README.txt
jalonedit/theme/browser/images/collagecolumn_icon.png
jalonedit/theme/browser/images/collagerow_icon.png
jalonedit/theme/browser/images/glossaire_icon.png
jalonedit/theme/browser/images/left-quote.gif
jalonedit/theme/browser/images/right-quote.gif
jalonedit/theme/browser/images/navigation/crumbs.png
jalonedit/theme/browser/images/navigation/crumbs_home.png
jalonedit/theme/browser/images/navigation/cours/activite.png
jalonedit/theme/browser/images/navigation/cours/attention.png
jalonedit/theme/browser/images/navigation/cours/citation.png
jalonedit/theme/browser/images/navigation/cours/complement.png
jalonedit/theme/browser/images/navigation/cours/conclusion.png
jalonedit/theme/browser/images/navigation/cours/confere.png
jalonedit/theme/browser/images/navigation/cours/conseil.png
jalonedit/theme/browser/images/navigation/cours/definition.png
jalonedit/theme/browser/images/navigation/cours/ensavoirplus.png
jalonedit/theme/browser/images/navigation/cours/exemple.png
jalonedit/theme/browser/images/navigation/cours/exercice.png
jalonedit/theme/browser/images/navigation/cours/explication.png
jalonedit/theme/browser/images/navigation/cours/internet.png
jalonedit/theme/browser/images/navigation/cours/introduction.png
jalonedit/theme/browser/images/navigation/cours/lien_interne.png
jalonedit/theme/browser/images/navigation/cours/media.png
jalonedit/theme/browser/images/navigation/cours/methode.png
jalonedit/theme/browser/images/navigation/cours/note.png
