Metadata-Version: 1.1
Name: jalonedit.theme
Version: 1.1
Summary: UNKNOWN
Home-page: http://svn.plone.org/svn/collective/
Author: Bordonado Christophe (Université Nice Sophia Antipolis Service TICE)
Author-email: tice@unice.fr
License: GPL
Platform: UNKNOWN
Classifier: Framework :: Plone
Classifier: Programming Language :: Python
